{
  "Комсомольский": [
    {
      "text": "Татнефть — работает (24/7)",
      "rating": 4,
      "source": "osm_active"
    },
    {
      "text": "Газпром — работает (24/7)",
      "rating": 4,
      "source": "osm_active"
    },
    {
      "text": "Lada Dеталь — работает (Mo-Su 08:00-19:00)",
      "rating": 4,
      "source": "osm_active"
    },
    {
      "text": "Пятёрочка — работает (08:00-22:00)",
      "rating": 4,
      "source": "osm_active"
    },
    {
      "text": "Набережные Челны 423802 — работает (Mo-Fr 08:00-20:00; Sa-Su 09:00-18:00)",
      "rating": 4,
      "source": "osm_active"
    },
    {
      "text": "Вита Экспресс — работает (Mo-Su 08:00-20:00)",
      "rating": 4,
      "source": "osm_active"
    },
    {
      "text": "Впрок — работает (Mo-Sa 09:00-20:00; Su 09:00-19:00)",
      "rating": 4,
      "source": "osm_active"
    },
    {
      "text": "Железо — работает (Mo-Fr 08:00-19:00; Sa-Su 09:00-18:00)",
      "rating": 4,
      "source": "osm_active"
    },
    {
      "text": "Irbis — работает (24/7)",
      "rating": 4,
      "source": "osm_active"
    },
    {
      "text": "Пятёрочка — работает (08:00-22:30)",
      "rating": 4,
      "source": "osm_active"
    },
    {
      "text": "Мидкам — работает (Mo-Fr 08:00-17:00; Sa 08:00-13:00)",
      "rating": 4,
      "source": "osm_active"
    },
    {
      "text": "Челны-бампер — работает (Mo-Su 08:00-17:00)",
      "rating": 4,
      "source": "osm_active"
    },
    {
      "text": "Валерия — работает (Mo-Fr 08:30-21:30)",
      "rating": 4,
      "source": "osm_active"
    },
    {
      "text": "Чио Чио — работает (Mo-Su 09:00-20:00)",
      "rating": 4,
      "source": "osm_active"
    },
    {
      "text": "Coffee Like — работает (Mo-Su 10:00-22:00)",
      "rating": 4,
      "source": "osm_active"
    },
    {
      "text": "Пятёрочка — работает (08:00-22:00)",
      "rating": 4,
      "source": "osm_active"
    },
    {
      "text": "Автостекло — работает (Mo-Sa 10:00-16:00)",
      "rating": 4,
      "source": "osm_active"
    },
    {
      "text": "МИБС — работает (07:00-23:00)",
      "rating": 4,
      "source": "osm_active"
    },
    {
      "text": "Находка — работает (Mo-Su 8:00-21:00)",
      "rating": 4,
      "source": "osm_active"
    },
    {
      "text": "Ozon — работает (Mo-Su 09:00-21:00)",
      "rating": 4,
      "source": "osm_active"
    },
    {
      "text": "Находка — работает (Mo-Su 8:00-21:00)",
      "rating": 4,
      "source": "osm_active"
    },
    {
      "text": "СДЭК — работает (Mo-Fr 10:00-20:00; Sa-Su 10:00-18:00)",
      "rating": 4,
      "source": "osm_active"
    },
    {
      "text": "СДЭК — недоступен",
      "rating": 2,
      "source": "osm_access"
    },
    {
      "text": "СДЭК — работает (Mo-Su 09:00-20:00)",
      "rating": 4,
      "source": "osm_active"
    },
    {
      "text": "Ozon — работает (Mo-Su 09:00-21:00)",
      "rating": 4,
      "source": "osm_active"
    },
    {
      "text": "Ozon — работает (Mo-Su 09:00-21:00)",
      "rating": 4,
      "source": "osm_active"
    },
    {
      "text": "Ozon — работает (Mo-Su 09:00-21:00)",
      "rating": 4,
      "source": "osm_active"
    },
    {
      "text": "Ozon — недоступен",
      "rating": 2,
      "source": "osm_access"
    },
    {
      "text": "Ozon — работает (Mo-Su 09:00-21:00)",
      "rating": 4,
      "source": "osm_active"
    },
    {
      "text": "Магнит Маркет — работает (Mo-Su 10:00-19:00)",
      "rating": 4,
      "source": "osm_active"
    },
    {
      "text": "Магнит Маркет — работает (Mo-Su 10:00-19:00)",
      "rating": 4,
      "source": "osm_active"
    },
    {
      "text": "Магнит Маркет — работает (Mo-Su 10:00-19:00)",
      "rating": 4,
      "source": "osm_active"
    },
    {
      "text": "Фасоль — работает (Mo-Su 07:00-21:00)",
      "rating": 4,
      "source": "osm_active"
    },
    {
      "text": "Ozon — работает (Mo-Su 09:00-21:00)",
      "rating": 4,
      "source": "osm_active"
    },
    {
      "text": "Ислам — работает (Mo-Su 09:00-20:00)",
      "rating": 4,
      "source": "osm_active"
    },
    {
      "text": "Мебельвсем — работает (Mo-Su 09:00-19:00)",
      "rating": 4,
      "source": "osm_active"
    },
    {
      "text": "Айсберг — работает (Mo-Su 09:00-18:00)",
      "rating": 4,
      "source": "osm_active"
    },
    {
      "text": "ЖБИ-Партнер — работает (Mo-Fr 07:00-17:00)",
      "rating": 4,
      "source": "osm_active"
    },
    {
      "text": "Каматехника — работает (Mo-Fr 08:00-17:00)",
      "rating": 4,
      "source": "osm_active"
    },
    {
      "text": "Ozon — работает (Mo-Su 09:00-21:00)",
      "rating": 4,
      "source": "osm_active"
    },
    {
      "text": "Ozon — работает (Mo-Su 09:00-21:00)",
      "rating": 4,
      "source": "osm_active"
    },
    {
      "text": "Челны Хлеб — работает (PH,Mo-Su 08:00-22:00)",
      "rating": 4,
      "source": "osm_active"
    },
    {
      "text": "ArtFish — работает (Mo-Su 00:00-00:00)",
      "rating": 4,
      "source": "osm_active"
    },
    {
      "text": "Дом инструмента — работает (Mo-Fr 08:00-18:00; Sa 09:00-17:00; Su 09:00-16:00)",
      "rating": 4,
      "source": "osm_active"
    },
    {
      "text": "Машиностроитель — работает (Mo-Fr 08:00-17:00)",
      "rating": 4,
      "source": "osm_active"
    },
    {
      "text": "Пятёрочка — работает (07:30-22:00)",
      "rating": 4,
      "source": "osm_active"
    },
    {
      "text": "Пятёрочка — работает (08:00-22:00)",
      "rating": 4,
      "source": "osm_active"
    },
    {
      "text": "Пятёрочка — работает (08:00-22:30)",
      "rating": 4,
      "source": "osm_active"
    },
    {
      "text": "Пятёрочка — работает (09:00-22:00)",
      "rating": 4,
      "source": "osm_active"
    },
    {
      "text": "ВсеИнструменты.ру — работает (Mo-Su 09:00-20:00)",
      "rating": 4,
      "source": "osm_active"
    },
    {
      "text": "Пятёрочка — работает (08:00-22:30)",
      "rating": 4,
      "source": "osm_active"
    },
    {
      "text": "Пятёрочка — работает (08:00-22:00)",
      "rating": 4,
      "source": "osm_active"
    },
    {
      "text": "Пятёрочка — работает (07:30-22:00)",
      "rating": 4,
      "source": "osm_active"
    },
    {
      "text": "Пятёрочка — работает (24/7)",
      "rating": 4,
      "source": "osm_active"
    },
    {
      "text": "Lada Dеталь — работает (Mo-Su 08:00-17:00)",
      "rating": 4,
      "source": "osm_active"
    },
    {
      "text": "Камторгсервис — работает (Mo-Fr 08:00-20:00)",
      "rating": 4,
      "source": "osm_active"
    },
    {
      "text": "Автомаркет — работает (Mo-Fr 09:00-18:00; Sa 09:00-16:00)",
      "rating": 4,
      "source": "osm_active"
    },
    {
      "text": "Лидертрак — работает (24/7)",
      "rating": 4,
      "source": "osm_active"
    },
    {
      "text": "ХозCнаб — работает (Mo-Fr 08:00-12:00,13:00-16:10)",
      "rating": 4,
      "source": "osm_active"
    },
    {
      "text": "Дом поликарбоната — работает (Mo-Fr 08:00-17:00; Sa 08:00-15:00; Su 08:00-13:00)",
      "rating": 4,
      "source": "osm_active"
    },
    {
      "text": "Татсталь — работает (Mo-Su 08:00-18:00)",
      "rating": 4,
      "source": "osm_active"
    },
    {
      "text": "Пятёрочка — работает (08:00-22:00)",
      "rating": 4,
      "source": "osm_active"
    },
    {
      "text": "Пятёрочка — работает (08:00-22:00)",
      "rating": 4,
      "source": "osm_active"
    },
    {
      "text": "Вита Экспресс — работает (Mo-Fr 08:00-21:00; Sa-Su 08:00-20:00)",
      "rating": 4,
      "source": "osm_active"
    },
    {
      "text": "Артстекло — работает (Mo-Fr 07:30-16:30)",
      "rating": 4,
      "source": "osm_active"
    },
    {
      "text": "Дети логозайки — работает (Mo-Fr 10:00-20:00)",
      "rating": 4,
      "source": "osm_active"
    },
    {
      "text": "Voge — работает (Mo-Sa 09:00-18:00; Su 09:00-16:00)",
      "rating": 4,
      "source": "osm_active"
    },
    {
      "text": "Food сервис — работает (Mo-Fr 09:00-18:00; Sa 10:00-14:00)",
      "rating": 4,
      "source": "osm_active"
    },
    {
      "text": "Находка — работает (Mo-Su 08:00-21:00)",
      "rating": 4,
      "source": "osm_active"
    },
    {
      "text": "Дар групп — работает (Mo-Sa 09:00-17:00; Su 10:00-16:00)",
      "rating": 4,
      "source": "osm_active"
    },
    {
      "text": "Neva dental — работает (Mo-Su 09:00-21:00)",
      "rating": 4,
      "source": "osm_active"
    },
    {
      "text": "Вита Экспресс — работает (Mo-Su 08:00-20:00)",
      "rating": 4,
      "source": "osm_active"
    },
    {
      "text": "ВсеИнструменты.ру — работает (Mo-Su 09:00-20:00)",
      "rating": 4,
      "source": "osm_active"
    },
    {
      "text": "Пятёрочка — работает (08:00-22:00)",
      "rating": 4,
      "source": "osm_active"
    },
    {
      "text": "Пятёрочка — работает (08:00-22:00)",
      "rating": 4,
      "source": "osm_active"
    },
    {
      "text": "Арт Сварка — работает (Mo-Fr 08:00-17:00; Sa 09:00-15:00)",
      "rating": 4,
      "source": "osm_active"
    },
    {
      "text": "МТЗ-Челны — работает (Mo-Fr 08:00-17:00; Sa 08:00-15:00)",
      "rating": 4,
      "source": "osm_active"
    },
    {
      "text": "Альт Мед — работает (Mo-Fr 07:00-20:00; Sa 07:00-13:30)",
      "rating": 4,
      "source": "osm_active"
    },
    {
      "text": "Дуэт — работает (Mo-Su 08:00-21:00)",
      "rating": 4,
      "source": "osm_active"
    },
    {
      "text": "Деревяшка — работает (Mo-Fr 08:00-17:00; Sa 09:00-13:00)",
      "rating": 4,
      "source": "osm_active"
    },
    {
      "text": "Суши House — работает (Fr-Sa 10:00-22:30; Mo-Th 10:00-21:30; Su 10:00-22:00)",
      "rating": 4,
      "source": "osm_active"
    },
    {
      "text": "Фармленд — работает (Mo-Su 08:00-21:00)",
      "rating": 4,
      "source": "osm_active"
    },
    {
      "text": "Ozon — работает (Mo-Su 09:00-21:00)",
      "rating": 4,
      "source": "osm_active"
    },
    {
      "text": "Florans — работает (Mo-Su 09:00-20:00)",
      "rating": 4,
      "source": "osm_active"
    },
    {
      "text": "Некст — работает (Mo-Sa 09:00-17:00)",
      "rating": 4,
      "source": "osm_active"
    },
    {
      "text": "Irbis — работает (24/7)",
      "rating": 4,
      "source": "osm_active"
    },
    {
      "text": "Татнефть — работает (24/7)",
      "rating": 4,
      "source": "osm_active"
    },
    {
      "text": "Таиф-НК — работает (24/7)",
      "rating": 4,
      "source": "osm_active"
    },
    {
      "text": "Фармленд — работает (Mo-Su 08:00-21:00)",
      "rating": 4,
      "source": "osm_active"
    },
    {
      "text": "Татнефть — работает (24/7)",
      "rating": 4,
      "source": "osm_active"
    },
    {
      "text": "Государственная сеть — работает (Mo-Fr 07:30-17:00; Sa 08:00-12:00)",
      "rating": 4,
      "source": "osm_active"
    },
    {
      "text": "Государственная сеть — работает (Mo-Fr 07:30-18:30; Sa 08:00-14:00)",
      "rating": 4,
      "source": "osm_active"
    },
    {
      "text": "Технониколь — работает (Mo-Fr 08:00-17:00)",
      "rating": 4,
      "source": "osm_active"
    },
    {
      "text": "Татнефть — работает (24/7)",
      "rating": 4,
      "source": "osm_active"
    },
    {
      "text": "Детский сад № 128 «Шаян» — работает (Mo-Fr 06:00-18:00)",
      "rating": 4,
      "source": "osm_active"
    },
    {
      "text": "Teboil — работает (Mo-Su 00:10-03:45,04:00-23:55)",
      "rating": 4,
      "source": "osm_active"
    },
    {
      "text": "Много магазинов (23)",
      "rating": 5,
      "source": "infra"
    },
    {
      "text": "Транспорт норм (13)",
      "rating": 4,
      "source": "infra"
    },
    {
      "text": "Парков нет",
      "rating": 2,
      "source": "infra"
    },
    {
      "text": "Площадки (49)",
      "rating": 5,
      "source": "infra"
    },
    {
      "text": "Есть поликлиника",
      "rating": 4,
      "source": "infra"
    },
    {
      "text": "Школы (2), садики (10)",
      "rating": 5,
      "source": "infra"
    },
    {
      "text": "Развитый район",
      "rating": 5,
      "source": "infra"
    }
  ],
  "Центральный": [
    {
      "text": "Транснефтепродукт — работает (24/7)",
      "rating": 4,
      "source": "osm_active"
    },
    {
      "text": "Полёт — работает (24/7)",
      "rating": 4,
      "source": "osm_active"
    },
    {
      "text": "Пятёрочка — работает (08:00-22:00)",
      "rating": 4,
      "source": "osm_active"
    },
    {
      "text": "Набережные Челны 423812 — работает (Mo-Fr 08:00-13:00,14:00-20:00; Sa-Su 09:00-13:00,14:00-18:00)",
      "rating": 4,
      "source": "osm_active"
    },
    {
      "text": "Почта Банк — недоступен",
      "rating": 2,
      "source": "osm_access"
    },
    {
      "text": "Таиф-НК — работает (24/7)",
      "rating": 4,
      "source": "osm_active"
    },
    {
      "text": "Люкс — работает (24/7)",
      "rating": 4,
      "source": "osm_active"
    },
    {
      "text": "СервисКар — работает (Mo-Fr 08:00-17:00; Sa 09:00-14:00)",
      "rating": 4,
      "source": "osm_active"
    },
    {
      "text": "Билайн — работает (Mo-Sa 09:00-20:00;Su 09:00-19:00)",
      "rating": 4,
      "source": "osm_active"
    },
    {
      "text": "Пятёрочка — работает (08:00-22:00)",
      "rating": 4,
      "source": "osm_active"
    },
    {
      "text": "Набережные Челны 423814 — работает (Mo-Fr 10:00-13:00,14:00-19:00; Sa-Su 10:00-16:00)",
      "rating": 4,
      "source": "osm_active"
    },
    {
      "text": "ВТБ — работает (Mo-Fr 09:00-19:00; Sa 10:00-15:00)",
      "rating": 4,
      "source": "osm_active"
    },
    {
      "text": "ВТБ — недоступен",
      "rating": 2,
      "source": "osm_access"
    },
    {
      "text": "Впрок — работает (Mo-Su 09:00-19:00)",
      "rating": 4,
      "source": "osm_active"
    },
    {
      "text": "Впрок — работает (Mo-Su 09:00-19:00)",
      "rating": 4,
      "source": "osm_active"
    },
    {
      "text": "Татнефть — работает (24/7)",
      "rating": 4,
      "source": "osm_active"
    },
    {
      "text": "Колобок — работает (08:00-21:00)",
      "rating": 4,
      "source": "osm_active"
    },
    {
      "text": "Тольяттинский центр запасных частей — работает (Mo-Su 09:00-17:00)",
      "rating": 4,
      "source": "osm_active"
    },
    {
      "text": "Alphard — работает (Mo-Su 10:00-18:00)",
      "rating": 4,
      "source": "osm_active"
    },
    {
      "text": "ООО Энергостандарт+ — работает (Mo-Fr 08:00-17:00)",
      "rating": 4,
      "source": "osm_active"
    },
    {
      "text": "Энергобанк — работает (Mo-Fr 09:00-19:30; Sa 10:00-15:00)",
      "rating": 4,
      "source": "osm_active"
    },
    {
      "text": "Fusion — работает (10:00-19:00)",
      "rating": 4,
      "source": "osm_active"
    },
    {
      "text": "Askona — работает (Mo-Su 10:00-21:00)",
      "rating": 4,
      "source": "osm_active"
    },
    {
      "text": "Askona — работает (Mo-Su 10:00-19:00)",
      "rating": 4,
      "source": "osm_active"
    },
    {
      "text": "Газпром АГНКС — работает (24/7)",
      "rating": 4,
      "source": "osm_active"
    },
    {
      "text": "Lazurit — работает (Mo-Sa 10:00-20:00;Su 10:00-19:00)",
      "rating": 4,
      "source": "osm_active"
    },
    {
      "text": "Атриум — работает (10:00-19:00)",
      "rating": 4,
      "source": "osm_active"
    },
    {
      "text": "Вита Центральная — работает (Mo-Su 08:00-21:00)",
      "rating": 4,
      "source": "osm_active"
    },
    {
      "text": "Планета здоровья — работает (24/7)",
      "rating": 4,
      "source": "osm_active"
    },
    {
      "text": "Сбербанк — работает (Mo-Fr 08:30-18:30;Sa 08:30-15:30)",
      "rating": 4,
      "source": "osm_active"
    },
    {
      "text": "Посуда центр — работает (09:00-20:00)",
      "rating": 4,
      "source": "osm_active"
    },
    {
      "text": "ПекАринка — работает (24/7)",
      "rating": 4,
      "source": "osm_active"
    },
    {
      "text": "Ангстрем — работает (Mo-Sa 10:00-20:00;Su 10:00-19:00)",
      "rating": 4,
      "source": "osm_active"
    },
    {
      "text": "Сафран — работает (08:00-22:00)",
      "rating": 4,
      "source": "osm_active"
    },
    {
      "text": "Lorena — работает (Mo-Su 10:00-20:00)",
      "rating": 4,
      "source": "osm_active"
    },
    {
      "text": "Улыбка радуги — работает (09:00-21:00)",
      "rating": 4,
      "source": "osm_active"
    },
    {
      "text": "Планета — работает (09:00-20:00)",
      "rating": 4,
      "source": "osm_active"
    },
    {
      "text": "Додо Пицца — работает (Mo-Su 10:00-22:00)",
      "rating": 4,
      "source": "osm_active"
    },
    {
      "text": "Моторыч — работает (Mo-Fr 09:00-18:00; Sa 10:00-17:00)",
      "rating": 4,
      "source": "osm_active"
    },
    {
      "text": "Набережные Челны 423804 — работает (Mo-Fr 08:00-13:00,14:00-16:30)",
      "rating": 4,
      "source": "osm_active"
    },
    {
      "text": "Lazurit — работает (Mo-Su 10:00-20:00)",
      "rating": 4,
      "source": "osm_active"
    },
    {
      "text": "Находка — работает (Mo-Su 8:00-21:00)",
      "rating": 4,
      "source": "osm_active"
    },
    {
      "text": "Кат Сервис — работает (Mo-Su 09:00-19:00)",
      "rating": 4,
      "source": "osm_active"
    },
    {
      "text": "ИНТЕРГАЗСЕРВИС — работает (Mo-Fr 09:00-17:00)",
      "rating": 4,
      "source": "osm_active"
    },
    {
      "text": "Победа — работает (Mo-Su 08:00-21:00)",
      "rating": 4,
      "source": "osm_active"
    },
    {
      "text": "Быстроденьги — работает (Mo-Sa 09:00-20:00;Su 10:00-19:00)",
      "rating": 4,
      "source": "osm_active"
    },
    {
      "text": "Ozon — работает (Mo-Su 09:00-21:00)",
      "rating": 4,
      "source": "osm_active"
    },
    {
      "text": "Ozon — работает (Mo-Su 09:00-21:00)",
      "rating": 4,
      "source": "osm_active"
    },
    {
      "text": "Автоцифра — работает (Mo-Su 08:00-17:00)",
      "rating": 4,
      "source": "osm_active"
    },
    {
      "text": "Автоцифра — работает (Mo-Su 09:00-20:30)",
      "rating": 4,
      "source": "osm_active"
    },
    {
      "text": "МТС — работает (Mo-Su 09:00-20:00)",
      "rating": 4,
      "source": "osm_active"
    },
    {
      "text": "Fandeco — работает (Mo-Su 09:00-20:00)",
      "rating": 4,
      "source": "osm_active"
    },
    {
      "text": "Билайн — работает (Mo-Su 09:00-20:00)",
      "rating": 4,
      "source": "osm_active"
    },
    {
      "text": "Вита Центральная — работает (24/7)",
      "rating": 4,
      "source": "osm_active"
    },
    {
      "text": "Онлайн Трейд — работает (Mo-Su 10:00-21:00)",
      "rating": 4,
      "source": "osm_active"
    },
    {
      "text": "Библиотека-филиал № 24 — работает (Mo-Fr 10:00-18:00)",
      "rating": 4,
      "source": "osm_active"
    },
    {
      "text": "Есть Библиотека-филиал № 24 (library)",
      "rating": 4,
      "source": "osm_positive"
    },
    {
      "text": "Центр медицинских справок — работает (Mo-Fr 08:00-17:30; Sa 09:00-12:00)",
      "rating": 4,
      "source": "osm_active"
    },
    {
      "text": "Автолидер — работает (Mo-Fr 08:00-18:00; Sa-Su 08:00-16:00)",
      "rating": 4,
      "source": "osm_active"
    },
    {
      "text": "ГазМаркет — работает (Mo-Fr 08:00-19:00; Sa 08:00-17:00; Su 08:00-16:00)",
      "rating": 4,
      "source": "osm_active"
    },
    {
      "text": "Cobra — работает (Mo-Fr 08:00-17:00; Sa 09:00-14:00)",
      "rating": 4,
      "source": "osm_active"
    },
    {
      "text": "Caramel — работает (Mo-Su 08:00-19:00)",
      "rating": 4,
      "source": "osm_active"
    },
    {
      "text": "Камкабель — работает (Mo-Sa 08:00-17:00)",
      "rating": 4,
      "source": "osm_active"
    },
    {
      "text": "Грааль — работает (Mo-Su 09:00-21:00)",
      "rating": 4,
      "source": "osm_active"
    },
    {
      "text": "Tedocolor — работает (Mo-Fr 09:00-18:00; Sa 09:00-15:00)",
      "rating": 4,
      "source": "osm_active"
    },
    {
      "text": "Real Parts — работает (Mo-Sa 08:00-17:00; Su 08:00-15:00)",
      "rating": 4,
      "source": "osm_active"
    },
    {
      "text": "Ormatek — работает (Mo-Su 10:00-21:00)",
      "rating": 4,
      "source": "osm_active"
    },
    {
      "text": "Хайран — работает (Th-Sa 12:00-00:00)",
      "rating": 4,
      "source": "osm_active"
    },
    {
      "text": "Управдом — работает (Mo-Su 09:00-19:00)",
      "rating": 4,
      "source": "osm_active"
    },
    {
      "text": "Агрегат мастер — работает (Mo-Fr 08:00-19:00)",
      "rating": 4,
      "source": "osm_active"
    },
    {
      "text": "SvetFar — работает (Mo-Fr 08:00-17:00)",
      "rating": 4,
      "source": "osm_active"
    },
    {
      "text": "Ремкузов116 — работает (Mo-Sa 08:00-18:00; Su 10:00-15:00)",
      "rating": 4,
      "source": "osm_active"
    },
    {
      "text": "Гамма+ — работает (Mo-Su 08:00-18:00)",
      "rating": 4,
      "source": "osm_active"
    },
    {
      "text": "Рыболов Робинзон — работает (Fr-Sa 09:00-20:00; Mo-Th,Su 09:00-19:00)",
      "rating": 4,
      "source": "osm_active"
    },
    {
      "text": "Viola — работает (Mo-Su 08:00-20:00)",
      "rating": 4,
      "source": "osm_active"
    },
    {
      "text": "Ворота + — работает (Mo-Fr 08:00-17:00; Sa 09:00-14:00)",
      "rating": 4,
      "source": "osm_active"
    },
    {
      "text": "Много плитки — работает (Mo-Fr 09:00-17:00; Sa 09:00-16:00)",
      "rating": 4,
      "source": "osm_active"
    },
    {
      "text": "Автоэмали — работает (Mo-Sa 09:00-18:00; Su 09:00-16:00)",
      "rating": 4,
      "source": "osm_active"
    },
    {
      "text": "Агрозапчасть-м — работает (Mo-Fr 08:00-16:00; Sa 08:00-12:00)",
      "rating": 4,
      "source": "osm_active"
    },
    {
      "text": "Экология Поволжья — работает (Mo-Su 08:00-20:00)",
      "rating": 4,
      "source": "osm_active"
    },
    {
      "text": "Ozon — работает (Mo-Su 09:00-21:00)",
      "rating": 4,
      "source": "osm_active"
    },
    {
      "text": "Ozon — работает (Mo-Su 09:00-21:00)",
      "rating": 4,
      "source": "osm_active"
    },
    {
      "text": "Соир — работает (Mo-Fr 08:00-17:00)",
      "rating": 4,
      "source": "osm_active"
    },
    {
      "text": "Феникс — работает (Mo-Fr 08:00-17:00)",
      "rating": 4,
      "source": "osm_active"
    },
    {
      "text": "Dark side — работает (Mo-Fr 08:00-18:00; Sa-Su 09:00-16:00)",
      "rating": 4,
      "source": "osm_active"
    },
    {
      "text": "Davita — работает (Mo-Su 09:00-20:00)",
      "rating": 4,
      "source": "osm_active"
    },
    {
      "text": "Пятёрочка — работает (08:00-22:00)",
      "rating": 4,
      "source": "osm_active"
    },
    {
      "text": "Дуть — работает (Fr-Sa 12:00-04:00; Mo-Th,Su 12:00-02:00)",
      "rating": 4,
      "source": "osm_active"
    },
    {
      "text": "Иммо сервис — работает (Mo-Su 08:00-17:00)",
      "rating": 4,
      "source": "osm_active"
    },
    {
      "text": "Eskbearing — работает (Mo-Fr 08:00-17:00)",
      "rating": 4,
      "source": "osm_active"
    },
    {
      "text": "Нужный инструмент — работает (Mo-Fr 08:00-18:00; Sa-Su 09:00-15:00)",
      "rating": 4,
      "source": "osm_active"
    },
    {
      "text": "Автосервис2.ру — работает (Mo-Fr 08:00-17:00)",
      "rating": 4,
      "source": "osm_active"
    },
    {
      "text": "Лидер Трейд — работает (Mo-Su 08:00-18:00)",
      "rating": 4,
      "source": "osm_active"
    },
    {
      "text": "Авторемонт.рт — работает (Mo-Fr 08:00-19:00; Sa-Su 08:00-15:00)",
      "rating": 4,
      "source": "osm_active"
    },
    {
      "text": "Европарк — работает (Mo-Fr 08:00-17:00; Sa 08:00-12:00)",
      "rating": 4,
      "source": "osm_active"
    },
    {
      "text": "Изометрия авто — работает (Mo-Fr 10:00-14:00,15:00-19:00; Sa 09:00-15:00)",
      "rating": 4,
      "source": "osm_active"
    },
    {
      "text": "Газавтомастер — работает (Mo-Fr 09:00-17:00; Sa 09:00-12:00)",
      "rating": 4,
      "source": "osm_active"
    },
    {
      "text": "Всё на Камаз — работает (Mo-Fr 08:30-16:00; Sa 09:00-15:00)",
      "rating": 4,
      "source": "osm_active"
    },
    {
      "text": "Мастер золотые руки — работает (Mo-Su 08:00-18:00)",
      "rating": 4,
      "source": "osm_active"
    },
    {
      "text": "Дизель-сервис — работает (Mo-Fr 08:00-12:00,13:00-17:00)",
      "rating": 4,
      "source": "osm_active"
    },
    {
      "text": "Агромадар — работает (Mo-Fr 08:00-17:00; Sa 08:00-13:00)",
      "rating": 4,
      "source": "osm_active"
    },
    {
      "text": "Автосфера — работает (Mo-Su 08:00-19:00)",
      "rating": 4,
      "source": "osm_active"
    },
    {
      "text": "КСЭ — работает (Mo-Fr 09:00-20:00; Sa 10:00-16:00)",
      "rating": 4,
      "source": "osm_active"
    },
    {
      "text": "Газпромнефть — работает (24/7)",
      "rating": 4,
      "source": "osm_active"
    },
    {
      "text": "Порт маркет — работает (Mo-Su 08:00-23:00)",
      "rating": 4,
      "source": "osm_active"
    },
    {
      "text": "Алиавто — работает (Mo-Sa 08:00-17:30; Su 08:00-16:30)",
      "rating": 4,
      "source": "osm_active"
    },
    {
      "text": "Иномарка — работает (Mo-Su 08:00-17:00)",
      "rating": 4,
      "source": "osm_active"
    },
    {
      "text": "Tvoe sedlo — работает (Mo-Su 09:00-21:00)",
      "rating": 4,
      "source": "osm_active"
    },
    {
      "text": "Аист — работает (Mo-Su 08:00-20:00)",
      "rating": 4,
      "source": "osm_active"
    },
    {
      "text": "Legenda.shop — работает (Mo-Su 10:00-19:00)",
      "rating": 4,
      "source": "osm_active"
    },
    {
      "text": "Сантехника-Онлайн — работает (Mo-Su 09:00-21:00)",
      "rating": 4,
      "source": "osm_active"
    },
    {
      "text": "Ozon — работает (Mo-Su 09:00-21:00)",
      "rating": 4,
      "source": "osm_active"
    },
    {
      "text": "Ozon — работает (Mo-Sa 08:00-20:00; Su 08:00-19:00)",
      "rating": 4,
      "source": "osm_active"
    },
    {
      "text": "Ozon — работает (Mo-Su 09:00-20:30)",
      "rating": 4,
      "source": "osm_active"
    },
    {
      "text": "Platinum — работает (Mo-Sa 09:00-19:00)",
      "rating": 4,
      "source": "osm_active"
    },
    {
      "text": "Lav — работает (Mo-Su 10:00-20:00)",
      "rating": 4,
      "source": "osm_active"
    },
    {
      "text": "Таиф-НК — работает (24/7)",
      "rating": 4,
      "source": "osm_active"
    },
    {
      "text": "ТрансТехСервис — работает (Mo-Sa 08:00-20:00; Su 09:00-19:00)",
      "rating": 4,
      "source": "osm_active"
    },
    {
      "text": "Darel — работает (Mo-Su 09:00-19:00)",
      "rating": 4,
      "source": "osm_active"
    },
    {
      "text": "Redi Auto — работает (Mo-Sa 08:00-18:00; Su 09:00-17:00)",
      "rating": 4,
      "source": "osm_active"
    },
    {
      "text": "Пятёрочка — работает (08:00-23:00)",
      "rating": 4,
      "source": "osm_active"
    },
    {
      "text": "Street pro detailing — работает (Mo-Su 09:00-19:00)",
      "rating": 4,
      "source": "osm_active"
    },
    {
      "text": "Moon — работает (Mo-Su 10:00-20:00)",
      "rating": 4,
      "source": "osm_active"
    },
    {
      "text": "Зеленика — работает (Mo-Su 08:00-16:30)",
      "rating": 4,
      "source": "osm_active"
    },
    {
      "text": "Фреш фрукт — работает (Mo-Su 09:00-19:00)",
      "rating": 4,
      "source": "osm_active"
    },
    {
      "text": "Кабинет психолога Ходаковой Натальи — работает (Mo-Su 08:00-19:00)",
      "rating": 4,
      "source": "osm_active"
    },
    {
      "text": "Бухара — работает (Mo-Su 09:00-21:00)",
      "rating": 4,
      "source": "osm_active"
    },
    {
      "text": "Риберра — работает (Mo-Fr 08:00-17:00)",
      "rating": 4,
      "source": "osm_active"
    },
    {
      "text": "Крепеж М7 — работает (Mo-Su 08:00-18:00)",
      "rating": 4,
      "source": "osm_active"
    },
    {
      "text": "Oil like — работает (Mo-Su 08:00-18:00)",
      "rating": 4,
      "source": "osm_active"
    },
    {
      "text": "Камойл — работает (Mo-Fr 09:00-17:00)",
      "rating": 4,
      "source": "osm_active"
    },
    {
      "text": "Мастер Лестниц — работает (Mo-Su 09:00-18:00)",
      "rating": 4,
      "source": "osm_active"
    },
    {
      "text": "Айпикор — работает (Mo-Sa 08:00-18:00)",
      "rating": 4,
      "source": "osm_active"
    },
    {
      "text": "Ninel Massage — работает (Mo-Su 09:00-20:00)",
      "rating": 4,
      "source": "osm_active"
    },
    {
      "text": "Mokko — работает (Mo-Su 09:00-20:00)",
      "rating": 4,
      "source": "osm_active"
    },
    {
      "text": "Sonmart — работает (Mo-Su 09:00-20:00)",
      "rating": 4,
      "source": "osm_active"
    },
    {
      "text": "Beauty Time A&S — работает (Mo-Fr 09:00-21:00; Sa-Su 10:00-18:00)",
      "rating": 4,
      "source": "osm_active"
    },
    {
      "text": "Дом стиля — работает (Mo-Fr 09:00-12:00,13:00-19:00; Sa-Su 10:00-12:00,13:00-17:00)",
      "rating": 4,
      "source": "osm_active"
    },
    {
      "text": "ГлавПоставка — работает (Mo-Fr 08:30-17:30; Sa 09:00-14:00)",
      "rating": 4,
      "source": "osm_active"
    },
    {
      "text": "Снек велл — работает (Mo-Fr 08:00-17:00)",
      "rating": 4,
      "source": "osm_active"
    },
    {
      "text": "Центр керамики — работает (Mo-Su 09:00-18:00)",
      "rating": 4,
      "source": "osm_active"
    },
    {
      "text": "Сервис комплект — работает (Mo-Sa 09:00-17:00)",
      "rating": 4,
      "source": "osm_active"
    },
    {
      "text": "Ozon — работает (Mo-Su 09:00-21:00)",
      "rating": 4,
      "source": "osm_active"
    },
    {
      "text": "ВсеИнструменты.ру — работает (Mo-Su 09:00-20:00)",
      "rating": 4,
      "source": "osm_active"
    },
    {
      "text": "Энова — работает (24/7)",
      "rating": 4,
      "source": "osm_active"
    },
    {
      "text": "Татнефть — работает (24/7)",
      "rating": 4,
      "source": "osm_active"
    },
    {
      "text": "Диалог-Авто — работает (Mo-Su 08:00-20:00)",
      "rating": 4,
      "source": "osm_active"
    },
    {
      "text": "Teboil — работает (24/7)",
      "rating": 4,
      "source": "osm_active"
    },
    {
      "text": "Irbis — работает (24/7)",
      "rating": 4,
      "source": "osm_active"
    },
    {
      "text": "ВТБ — работает (Mo-Fr 09:00-18:00)",
      "rating": 4,
      "source": "osm_active"
    },
    {
      "text": "ВТБ — недоступен",
      "rating": 2,
      "source": "osm_access"
    },
    {
      "text": "Grand Line — работает (Mo-Fr 08:00-18:00 Sat 10:00-15:00)",
      "rating": 4,
      "source": "osm_active"
    },
    {
      "text": "Домикс — работает (Mo-Su 09:00-20:00)",
      "rating": 4,
      "source": "osm_active"
    },
    {
      "text": "Государственная сеть — работает (Mo-Fr 08:00-20:00; Sa-Su 09:00-18:00)",
      "rating": 4,
      "source": "osm_active"
    },
    {
      "text": "Мегастрой — работает (Mo-Su 07:00-22:00)",
      "rating": 4,
      "source": "osm_active"
    },
    {
      "text": "Эксперт — работает (Mo-Fr 09:00-16:00)",
      "rating": 4,
      "source": "osm_active"
    },
    {
      "text": "Кама Плюс — работает (Mo-Sa 08:00-20:00; Su 08:00-19:00)",
      "rating": 4,
      "source": "osm_active"
    },
    {
      "text": "Вита Экспресс — работает (Mo-Su 08:00-21:00)",
      "rating": 4,
      "source": "osm_active"
    },
    {
      "text": "Много магазинов (15)",
      "rating": 5,
      "source": "infra"
    },
    {
      "text": "Отличный транспорт (16)",
      "rating": 5,
      "source": "infra"
    },
    {
      "text": "Парков нет",
      "rating": 2,
      "source": "infra"
    },
    {
      "text": "Площадки (21)",
      "rating": 5,
      "source": "infra"
    },
    {
      "text": "Есть поликлиника",
      "rating": 4,
      "source": "infra"
    },
    {
      "text": "Школы (6), садики (7)",
      "rating": 5,
      "source": "infra"
    },
    {
      "text": "Развитый район",
      "rating": 5,
      "source": "infra"
    }
  ],
  "Автозаводский": [
    {
      "text": "Автомастер+ — работает (24/7)",
      "rating": 4,
      "source": "osm_active"
    },
    {
      "text": "Триал-спорт — работает (Mo-Sa 10:00-20:00; Su 11:00-19:00)",
      "rating": 4,
      "source": "osm_active"
    },
    {
      "text": "Набережные Челны 423824 — работает (Mo-Th 09:00-13:00,14:00-16:30; Fr 09:00-13:00,14:00-15:30)",
      "rating": 4,
      "source": "osm_active"
    },
    {
      "text": "Татнефть — работает (24/7)",
      "rating": 4,
      "source": "osm_active"
    },
    {
      "text": "Онлайн Трейд — работает (Mo-Su 10:00-21:00)",
      "rating": 4,
      "source": "osm_active"
    },
    {
      "text": "Coffee Like — работает (Mo-Su 10:00-22:00)",
      "rating": 4,
      "source": "osm_active"
    },
    {
      "text": "Модульбанк — работает (Mo-Fr 09:00-18:00)",
      "rating": 4,
      "source": "osm_active"
    },
    {
      "text": "Вита Экспресс — работает (Mo-Su 08:00-20:00)",
      "rating": 4,
      "source": "osm_active"
    },
    {
      "text": "Ozon — работает (Mo-Su 09:00-21:00)",
      "rating": 4,
      "source": "osm_active"
    },
    {
      "text": "Алоэ — работает (Mo-Su 09:00-21:00)",
      "rating": 4,
      "source": "osm_active"
    },
    {
      "text": "Coffee Like — работает (Mo-Fr 07:30-17:30)",
      "rating": 4,
      "source": "osm_active"
    },
    {
      "text": "Восток-сервис — работает (Mo-Fr 08:00-18:00)",
      "rating": 4,
      "source": "osm_active"
    },
    {
      "text": "Столовая № 67 — работает (Mo-Su 07:00-21:00)",
      "rating": 4,
      "source": "osm_active"
    },
    {
      "text": "Ключевой момент — работает (Mo-Su 10:00-20:00)",
      "rating": 4,
      "source": "osm_active"
    },
    {
      "text": "Находка — работает (Mo-Su 08:00-21:00)",
      "rating": 4,
      "source": "osm_active"
    },
    {
      "text": "Lamore Mio — работает (Mo-Su 10:00-23:00)",
      "rating": 4,
      "source": "osm_active"
    },
    {
      "text": "Многофункциональный центр прикладных квалификаций машиностроения — работает (Mo-Fr 08:00-17:00)",
      "rating": 4,
      "source": "osm_active"
    },
    {
      "text": "Пятёрочка — работает (08:00-22:00)",
      "rating": 4,
      "source": "osm_active"
    },
    {
      "text": "Пятёрочка — работает (08:00-22:30)",
      "rating": 4,
      "source": "osm_active"
    },
    {
      "text": "Пятёрочка — работает (08:00-22:00)",
      "rating": 4,
      "source": "osm_active"
    },
    {
      "text": "Vecom — работает (Mo-Fr 09:00-18:00)",
      "rating": 4,
      "source": "osm_active"
    },
    {
      "text": "На колесах — работает (24/7)",
      "rating": 4,
      "source": "osm_active"
    },
    {
      "text": "Татнефть — работает (24/7)",
      "rating": 4,
      "source": "osm_active"
    },
    {
      "text": "Порт маркет — работает (Mo-Su 08:00-22:00)",
      "rating": 4,
      "source": "osm_active"
    },
    {
      "text": "Пятёрочка — работает (09:00-21:00)",
      "rating": 4,
      "source": "osm_active"
    },
    {
      "text": "ТрансТехСервис — работает (Mo-Sa 08:00-20:00; Su 09:00-17:00)",
      "rating": 4,
      "source": "osm_active"
    },
    {
      "text": "АртВорота — работает (Mo-Su 08:00-17:00)",
      "rating": 4,
      "source": "osm_active"
    },
    {
      "text": "Ozon — работает (Mo-Su 09:00-21:00)",
      "rating": 4,
      "source": "osm_active"
    },
    {
      "text": "Ozon — работает (Mo-Su 09:00-21:00)",
      "rating": 4,
      "source": "osm_active"
    },
    {
      "text": "Робот Мойка — работает (24/7)",
      "rating": 4,
      "source": "osm_active"
    },
    {
      "text": "Кровля — работает (Mo-Fr 08:00-17:00; Sa 08:00-15:00; Su 08:00-14:00)",
      "rating": 4,
      "source": "osm_active"
    },
    {
      "text": "Ремстудия — работает (Mo-Sa 08:30-18:00)",
      "rating": 4,
      "source": "osm_active"
    },
    {
      "text": "Алга-С — работает (Mo-Fr 09:00-17:00)",
      "rating": 4,
      "source": "osm_active"
    },
    {
      "text": "Завгар — работает (Mo-Su 08:00-19:00)",
      "rating": 4,
      "source": "osm_active"
    },
    {
      "text": "Avada auto — работает (Mo-Su 09:00-19:00)",
      "rating": 4,
      "source": "osm_active"
    },
    {
      "text": "Альфа электрик — работает (Mo-Fr 08:00-18:00; Sa 09:00-17:00; Su 09:00-16:00)",
      "rating": 4,
      "source": "osm_active"
    },
    {
      "text": "Irbis — работает (24/7)",
      "rating": 4,
      "source": "osm_active"
    },
    {
      "text": "Lecar — работает (Mo-Fr 08:00-19:00)",
      "rating": 4,
      "source": "osm_active"
    },
    {
      "text": "Мега-мойка — работает (24/7)",
      "rating": 4,
      "source": "osm_active"
    },
    {
      "text": "Лукойл — работает (24/7)",
      "rating": 4,
      "source": "osm_active"
    },
    {
      "text": "Irbis — работает (24/7)",
      "rating": 4,
      "source": "osm_active"
    },
    {
      "text": "Bosch Авто Сервис — работает (08:00-20:00)",
      "rating": 4,
      "source": "osm_active"
    },
    {
      "text": "Ozon — работает (Mo-Su 09:00-21:00)",
      "rating": 4,
      "source": "osm_active"
    },
    {
      "text": "Есть Орион (community_centre)",
      "rating": 4,
      "source": "osm_positive"
    },
    {
      "text": "Акибанк — работает (Mo-Fr 09:00-12:30,13:30-18:00)",
      "rating": 4,
      "source": "osm_active"
    },
    {
      "text": "Татнефть — работает (24/7)",
      "rating": 4,
      "source": "osm_active"
    },
    {
      "text": "Грин Лайн — работает (7:00-22:00)",
      "rating": 4,
      "source": "osm_active"
    },
    {
      "text": "Набережночелнинский городской суд — работает (Mo-Fr 08:00-17:00)",
      "rating": 4,
      "source": "osm_active"
    },
    {
      "text": "Мало магазинов (4)",
      "rating": 2,
      "source": "infra"
    },
    {
      "text": "Транспорт норм (8)",
      "rating": 4,
      "source": "infra"
    },
    {
      "text": "Парков нет",
      "rating": 2,
      "source": "infra"
    },
    {
      "text": "Площадки (6)",
      "rating": 5,
      "source": "infra"
    },
    {
      "text": "Нет поликлиники",
      "rating": 2,
      "source": "infra"
    }
  ]
}